[{"username": "vsochat", "memory_full_info": {"rss": 5361664, "vms": 245211136, "shared": 3514368, "text": 20971520, "lib": 0, "data": 213061632, "dirty": 0, "uss": 5246976, "pss": 5258240, "swap": 0}, "create_time": 1558275530.21, "cwd": "/scratch/users/vsochat", "cpu_affinity": [2, 3, 6, 7, 8, 9, 10], "pid": 3068, "connections": [], "cpu_percent": 0.0, "num_ctx_switches": {"voluntary": 23, "involuntary": 3}, "exe": "/usr/bin/singularity", "name": "singularity", "cpu_times": {"user": 0.0, "system": 0.0, "children_user": 0.0, "children_system": 0.0}, "cpu_num": 8, "status": "running", "cmdline": ["singularity", "run", "docker://vanessa/watchme-mnist", "/home/users/vsochat/.watchme/mnist/data/watchme-mnist-cpu-iter5-proc7.png"], "memory_percent": 0.008780611628483108, "io_counters": {"read_count": 13, "write_count": 0, "read_bytes": 544768, "write_bytes": 0, "read_chars": 4604, "write_chars": 0}, "ionice": {"ioclass": "IOPRIO_CLASS_NONE", "value": 0}, "num_threads": 6, "nice": 0, "num_fds": 4, "gids": {"real": 32264, "effetive": 32264, "saved": 32264}, "ppid": 3064, "uids": {"real": 9182, "effetive": 9182, "saved": 9182}, "open_files": 0, "SET_NPROC": "7", "ACTUAL_NPROC": "1", "HOSTNAME": "sh-18-12.int", "MAXMEMORY": "12", "SECONDS": "20"}, {"username": "vsochat", "create_time": 1558275530.21, "cpu_affinity": [2, 3, 6, 7, 8, 9, 10], "pid": 3068, "cpu_percent": 0.0, "num_ctx_switches": {"voluntary": 82, "involuntary": 3}, "name": "starter-suid", "cpu_times": {"user": 0.1, "system": 0.04, "children_user": 0.01, "children_system": 0.0}, "cpu_num": 7, "status": "sleeping", "cmdline": ["Singularity runtime parent"], "memory_percent": 0.01329600607259534, "ionice": {"ioclass": "IOPRIO_CLASS_NONE", "value": 0}, "num_threads": 7, "nice": 0, "gids": {"real": 32264, "effetive": 32264, "saved": 32264}, "ppid": 3064, "uids": {"real": 9182, "effetive": 9182, "saved": 0}, "SET_NPROC": "7", "ACTUAL_NPROC": "1", "HOSTNAME": "sh-18-12.int", "MAXMEMORY": "12", "SECONDS": "20"}, {"username": "vsochat", "create_time": 1558275530.21, "cpu_affinity": [2, 3, 6, 7, 8, 9, 10], "pid": 3068, "cpu_percent": 0.0, "num_ctx_switches": {"voluntary": 82, "involuntary": 3}, "name": "starter-suid", "cpu_times": {"user": 0.1, "system": 0.04, "children_user": 0.01, "children_system": 0.0}, "cpu_num": 7, "status": "sleeping", "cmdline": ["Singularity runtime parent"], "memory_percent": 0.01329600607259534, "ionice": {"ioclass": "IOPRIO_CLASS_NONE", "value": 0}, "num_threads": 7, "nice": 0, "gids": {"real": 32264, "effetive": 32264, "saved": 32264}, "ppid": 3064, "uids": {"real": 9182, "effetive": 9182, "saved": 0}, "SET_NPROC": "7", "ACTUAL_NPROC": "1", "HOSTNAME": "sh-18-12.int", "MAXMEMORY": "12", "SECONDS": "20"}, {"username": "vsochat", "create_time": 1558275530.21, "cpu_affinity": [2, 3, 6, 7, 8, 9, 10], "pid": 3068, "cpu_percent": 0.0, "num_ctx_switches": {"voluntary": 82, "involuntary": 3}, "name": "starter-suid", "cpu_times": {"user": 0.1, "system": 0.04, "children_user": 0.01, "children_system": 0.0}, "cpu_num": 7, "status": "sleeping", "cmdline": ["Singularity runtime parent"], "memory_percent": 0.01329600607259534, "ionice": {"ioclass": "IOPRIO_CLASS_NONE", "value": 0}, "num_threads": 7, "nice": 0, "gids": {"real": 32264, "effetive": 32264, "saved": 32264}, "ppid": 3064, "uids": {"real": 9182, "effetive": 9182, "saved": 0}, "SET_NPROC": "7", "ACTUAL_NPROC": "1", "HOSTNAME": "sh-18-12.int", "MAXMEMORY": "12", "SECONDS": "20"}, {"username": "vsochat", "create_time": 1558275530.21, "cpu_affinity": [2, 3, 6, 7, 8, 9, 10], "pid": 3068, "cpu_percent": 0.0, "num_ctx_switches": {"voluntary": 82, "involuntary": 3}, "name": "starter-suid", "cpu_times": {"user": 0.1, "system": 0.04, "children_user": 0.01, "children_system": 0.0}, "cpu_num": 7, "status": "sleeping", "cmdline": ["Singularity runtime parent"], "memory_percent": 0.01329600607259534, "ionice": {"ioclass": "IOPRIO_CLASS_NONE", "value": 0}, "num_threads": 7, "nice": 0, "gids": {"real": 32264, "effetive": 32264, "saved": 32264}, "ppid": 3064, "uids": {"real": 9182, "effetive": 9182, "saved": 0}, "SET_NPROC": "7", "ACTUAL_NPROC": "1", "HOSTNAME": "sh-18-12.int", "MAXMEMORY": "12", "SECONDS": "20"}, {"username": "vsochat", "create_time": 1558275530.21, "cpu_affinity": [2, 3, 6, 7, 8, 9, 10], "pid": 3068, "cpu_percent": 0.0, "num_ctx_switches": {"voluntary": 82, "involuntary": 3}, "name": "starter-suid", "cpu_times": {"user": 0.1, "system": 0.04, "children_user": 0.01, "children_system": 0.0}, "cpu_num": 7, "status": "sleeping", "cmdline": ["Singularity runtime parent"], "memory_percent": 0.01329600607259534, "ionice": {"ioclass": "IOPRIO_CLASS_NONE", "value": 0}, "num_threads": 7, "nice": 0, "gids": {"real": 32264, "effetive": 32264, "saved": 32264}, "ppid": 3064, "uids": {"real": 9182, "effetive": 9182, "saved": 0}, "SET_NPROC": "7", "ACTUAL_NPROC": "1", "HOSTNAME": "sh-18-12.int", "MAXMEMORY": "12", "SECONDS": "20"}, {"username": "vsochat", "create_time": 1558275530.21, "cpu_affinity": [2, 3, 6, 7, 8, 9, 10], "pid": 3068, "cpu_percent": 0.0, "num_ctx_switches": {"voluntary": 82, "involuntary": 3}, "name": "starter-suid", "cpu_times": {"user": 0.1, "system": 0.04, "children_user": 0.01, "children_system": 0.0}, "cpu_num": 7, "status": "sleeping", "cmdline": ["Singularity runtime parent"], "memory_percent": 0.01329600607259534, "ionice": {"ioclass": "IOPRIO_CLASS_NONE", "value": 0}, "num_threads": 7, "nice": 0, "gids": {"real": 32264, "effetive": 32264, "saved": 32264}, "ppid": 3064, "uids": {"real": 9182, "effetive": 9182, "saved": 0}, "SET_NPROC": "7", "ACTUAL_NPROC": "1", "HOSTNAME": "sh-18-12.int", "MAXMEMORY": "12", "SECONDS": "20"}, {"username": "vsochat", "create_time": 1558275530.21, "cpu_affinity": [2, 3, 6, 7, 8, 9, 10], "pid": 3068, "cpu_percent": 0.0, "num_ctx_switches": {"voluntary": 82, "involuntary": 3}, "name": "starter-suid", "cpu_times": {"user": 0.1, "system": 0.04, "children_user": 0.01, "children_system": 0.0}, "cpu_num": 7, "status": "sleeping", "cmdline": ["Singularity runtime parent"], "memory_percent": 0.01329600607259534, "ionice": {"ioclass": "IOPRIO_CLASS_NONE", "value": 0}, "num_threads": 7, "nice": 0, "gids": {"real": 32264, "effetive": 32264, "saved": 32264}, "ppid": 3064, "uids": {"real": 9182, "effetive": 9182, "saved": 0}, "SET_NPROC": "7", "ACTUAL_NPROC": "1", "HOSTNAME": "sh-18-12.int", "MAXMEMORY": "12", "SECONDS": "20"}, {"username": "vsochat", "create_time": 1558275530.21, "cpu_affinity": [2, 3, 6, 7, 8, 9, 10], "pid": 3068, "cpu_percent": 0.0, "num_ctx_switches": {"voluntary": 82, "involuntary": 3}, "name": "starter-suid", "cpu_times": {"user": 0.1, "system": 0.04, "children_user": 0.01, "children_system": 0.0}, "cpu_num": 7, "status": "sleeping", "cmdline": ["Singularity runtime parent"], "memory_percent": 0.01329600607259534, "ionice": {"ioclass": "IOPRIO_CLASS_NONE", "value": 0}, "num_threads": 7, "nice": 0, "gids": {"real": 32264, "effetive": 32264, "saved": 32264}, "ppid": 3064, "uids": {"real": 9182, "effetive": 9182, "saved": 0}, "SET_NPROC": "7", "ACTUAL_NPROC": "1", "HOSTNAME": "sh-18-12.int", "MAXMEMORY": "12", "SECONDS": "20"}, {"username": "vsochat", "create_time": 1558275530.21, "cpu_affinity": [2, 3, 6, 7, 8, 9, 10], "pid": 3068, "cpu_percent": 0.0, "num_ctx_switches": {"voluntary": 82, "involuntary": 3}, "name": "starter-suid", "cpu_times": {"user": 0.1, "system": 0.04, "children_user": 0.01, "children_system": 0.0}, "cpu_num": 7, "status": "sleeping", "cmdline": ["Singularity runtime parent"], "memory_percent": 0.01329600607259534, "ionice": {"ioclass": "IOPRIO_CLASS_NONE", "value": 0}, "num_threads": 7, "nice": 0, "gids": {"real": 32264, "effetive": 32264, "saved": 32264}, "ppid": 3064, "uids": {"real": 9182, "effetive": 9182, "saved": 0}, "SET_NPROC": "7", "ACTUAL_NPROC": "1", "HOSTNAME": "sh-18-12.int", "MAXMEMORY": "12", "SECONDS": "20"}, {"username": "vsochat", "create_time": 1558275530.21, "cpu_affinity": [2, 3, 6, 7, 8, 9, 10], "pid": 3068, "cpu_percent": 0.0, "num_ctx_switches": {"voluntary": 82, "involuntary": 3}, "name": "starter-suid", "cpu_times": {"user": 0.1, "system": 0.04, "children_user": 0.01, "children_system": 0.0}, "cpu_num": 7, "status": "sleeping", "cmdline": ["Singularity runtime parent"], "memory_percent": 0.01329600607259534, "ionice": {"ioclass": "IOPRIO_CLASS_NONE", "value": 0}, "num_threads": 7, "nice": 0, "gids": {"real": 32264, "effetive": 32264, "saved": 32264}, "ppid": 3064, "uids": {"real": 9182, "effetive": 9182, "saved": 0}, "SET_NPROC": "7", "ACTUAL_NPROC": "1", "HOSTNAME": "sh-18-12.int", "MAXMEMORY": "12", "SECONDS": "20"}, {"username": "vsochat", "create_time": 1558275530.21, "cpu_affinity": [2, 3, 6, 7, 8, 9, 10], "pid": 3068, "cpu_percent": 0.0, "num_ctx_switches": {"voluntary": 82, "involuntary": 3}, "name": "starter-suid", "cpu_times": {"user": 0.1, "system": 0.04, "children_user": 0.01, "children_system": 0.0}, "cpu_num": 7, "status": "sleeping", "cmdline": ["Singularity runtime parent"], "memory_percent": 0.01329600607259534, "ionice": {"ioclass": "IOPRIO_CLASS_NONE", "value": 0}, "num_threads": 7, "nice": 0, "gids": {"real": 32264, "effetive": 32264, "saved": 32264}, "ppid": 3064, "uids": {"real": 9182, "effetive": 9182, "saved": 0}, "SET_NPROC": "7", "ACTUAL_NPROC": "1", "HOSTNAME": "sh-18-12.int", "MAXMEMORY": "12", "SECONDS": "20"}, {"username": "vsochat", "create_time": 1558275530.21, "cpu_affinity": [2, 3, 6, 7, 8, 9, 10], "pid": 3068, "cpu_percent": 0.0, "num_ctx_switches": {"voluntary": 82, "involuntary": 3}, "name": "starter-suid", "cpu_times": {"user": 0.1, "system": 0.04, "children_user": 0.01, "children_system": 0.0}, "cpu_num": 7, "status": "sleeping", "cmdline": ["Singularity runtime parent"], "memory_percent": 0.01329600607259534, "ionice": {"ioclass": "IOPRIO_CLASS_NONE", "value": 0}, "num_threads": 7, "nice": 0, "gids": {"real": 32264, "effetive": 32264, "saved": 32264}, "ppid": 3064, "uids": {"real": 9182, "effetive": 9182, "saved": 0}, "SET_NPROC": "7", "ACTUAL_NPROC": "1", "HOSTNAME": "sh-18-12.int", "MAXMEMORY": "12", "SECONDS": "20"}, {"username": "vsochat", "create_time": 1558275530.21, "cpu_affinity": [2, 3, 6, 7, 8, 9, 10], "pid": 3068, "cpu_percent": 0.0, "num_ctx_switches": {"voluntary": 82, "involuntary": 3}, "name": "starter-suid", "cpu_times": {"user": 0.1, "system": 0.04, "children_user": 0.01, "children_system": 0.0}, "cpu_num": 7, "status": "sleeping", "cmdline": ["Singularity runtime parent"], "memory_percent": 0.01329600607259534, "ionice": {"ioclass": "IOPRIO_CLASS_NONE", "value": 0}, "num_threads": 7, "nice": 0, "gids": {"real": 32264, "effetive": 32264, "saved": 32264}, "ppid": 3064, "uids": {"real": 9182, "effetive": 9182, "saved": 0}, "SET_NPROC": "7", "ACTUAL_NPROC": "1", "HOSTNAME": "sh-18-12.int", "MAXMEMORY": "12", "SECONDS": "20"}, {"username": "vsochat", "create_time": 1558275530.21, "cpu_affinity": [2, 3, 6, 7, 8, 9, 10], "pid": 3068, "cpu_percent": 0.0, "num_ctx_switches": {"voluntary": 82, "involuntary": 3}, "name": "starter-suid", "cpu_times": {"user": 0.1, "system": 0.04, "children_user": 0.01, "children_system": 0.0}, "cpu_num": 7, "status": "sleeping", "cmdline": ["Singularity runtime parent"], "memory_percent": 0.01329600607259534, "ionice": {"ioclass": "IOPRIO_CLASS_NONE", "value": 0}, "num_threads": 7, "nice": 0, "gids": {"real": 32264, "effetive": 32264, "saved": 32264}, "ppid": 3064, "uids": {"real": 9182, "effetive": 9182, "saved": 0}, "SET_NPROC": "7", "ACTUAL_NPROC": "1", "HOSTNAME": "sh-18-12.int", "MAXMEMORY": "12", "SECONDS": "20"}, {"username": "vsochat", "create_time": 1558275530.21, "cpu_affinity": [2, 3, 6, 7, 8, 9, 10], "pid": 3068, "cpu_percent": 0.0, "num_ctx_switches": {"voluntary": 82, "involuntary": 3}, "name": "starter-suid", "cpu_times": {"user": 0.1, "system": 0.04, "children_user": 0.01, "children_system": 0.0}, "cpu_num": 7, "status": "sleeping", "cmdline": ["Singularity runtime parent"], "memory_percent": 0.01329600607259534, "ionice": {"ioclass": "IOPRIO_CLASS_NONE", "value": 0}, "num_threads": 7, "nice": 0, "gids": {"real": 32264, "effetive": 32264, "saved": 32264}, "ppid": 3064, "uids": {"real": 9182, "effetive": 9182, "saved": 0}, "SET_NPROC": "7", "ACTUAL_NPROC": "1", "HOSTNAME": "sh-18-12.int", "MAXMEMORY": "12", "SECONDS": "20"}, {"username": "vsochat", "create_time": 1558275530.21, "cpu_affinity": [2, 3, 6, 7, 8, 9, 10], "pid": 3068, "cpu_percent": 0.0, "num_ctx_switches": {"voluntary": 82, "involuntary": 3}, "name": "starter-suid", "cpu_times": {"user": 0.1, "system": 0.04, "children_user": 0.01, "children_system": 0.0}, "cpu_num": 7, "status": "sleeping", "cmdline": ["Singularity runtime parent"], "memory_percent": 0.01329600607259534, "ionice": {"ioclass": "IOPRIO_CLASS_NONE", "value": 0}, "num_threads": 7, "nice": 0, "gids": {"real": 32264, "effetive": 32264, "saved": 32264}, "ppid": 3064, "uids": {"real": 9182, "effetive": 9182, "saved": 0}, "SET_NPROC": "7", "ACTUAL_NPROC": "1", "HOSTNAME": "sh-18-12.int", "MAXMEMORY": "12", "SECONDS": "20"}, {"username": "vsochat", "create_time": 1558275530.21, "cpu_affinity": [2, 3, 6, 7, 8, 9, 10], "pid": 3068, "cpu_percent": 0.0, "num_ctx_switches": {"voluntary": 82, "involuntary": 3}, "name": "starter-suid", "cpu_times": {"user": 0.1, "system": 0.04, "children_user": 0.01, "children_system": 0.0}, "cpu_num": 7, "status": "sleeping", "cmdline": ["Singularity runtime parent"], "memory_percent": 0.01329600607259534, "ionice": {"ioclass": "IOPRIO_CLASS_NONE", "value": 0}, "num_threads": 7, "nice": 0, "gids": {"real": 32264, "effetive": 32264, "saved": 32264}, "ppid": 3064, "uids": {"real": 9182, "effetive": 9182, "saved": 0}, "SET_NPROC": "7", "ACTUAL_NPROC": "1", "HOSTNAME": "sh-18-12.int", "MAXMEMORY": "12", "SECONDS": "20"}, {"username": "vsochat", "create_time": 1558275530.21, "cpu_affinity": [2, 3, 6, 7, 8, 9, 10], "pid": 3068, "cpu_percent": 0.0, "num_ctx_switches": {"voluntary": 82, "involuntary": 3}, "name": "starter-suid", "cpu_times": {"user": 0.1, "system": 0.04, "children_user": 0.01, "children_system": 0.0}, "cpu_num": 7, "status": "sleeping", "cmdline": ["Singularity runtime parent"], "memory_percent": 0.01329600607259534, "ionice": {"ioclass": "IOPRIO_CLASS_NONE", "value": 0}, "num_threads": 7, "nice": 0, "gids": {"real": 32264, "effetive": 32264, "saved": 32264}, "ppid": 3064, "uids": {"real": 9182, "effetive": 9182, "saved": 0}, "SET_NPROC": "7", "ACTUAL_NPROC": "1", "HOSTNAME": "sh-18-12.int", "MAXMEMORY": "12", "SECONDS": "20"}, {"username": "vsochat", "create_time": 1558275530.21, "cpu_affinity": [2, 3, 6, 7, 8, 9, 10], "pid": 3068, "cpu_percent": 0.0, "num_ctx_switches": {"voluntary": 82, "involuntary": 3}, "name": "starter-suid", "cpu_times": {"user": 0.1, "system": 0.04, "children_user": 0.01, "children_system": 0.0}, "cpu_num": 7, "status": "sleeping", "cmdline": ["Singularity runtime parent"], "memory_percent": 0.013302107956979274, "ionice": {"ioclass": "IOPRIO_CLASS_NONE", "value": 0}, "num_threads": 7, "nice": 0, "gids": {"real": 32264, "effetive": 32264, "saved": 32264}, "ppid": 3064, "uids": {"real": 9182, "effetive": 9182, "saved": 0}, "SET_NPROC": "7", "ACTUAL_NPROC": "1", "HOSTNAME": "sh-18-12.int", "MAXMEMORY": "12", "SECONDS": "20"}, {"username": "vsochat", "create_time": 1558275530.21, "cpu_affinity": [2, 3, 6, 7, 8, 9, 10], "pid": 3068, "cpu_percent": 0.0, "num_ctx_switches": {"voluntary": 82, "involuntary": 3}, "name": "starter-suid", "cpu_times": {"user": 0.1, "system": 0.04, "children_user": 0.01, "children_system": 0.0}, "cpu_num": 7, "status": "sleeping", "cmdline": ["Singularity runtime parent"], "memory_percent": 0.013302107956979274, "ionice": {"ioclass": "IOPRIO_CLASS_NONE", "value": 0}, "num_threads": 7, "nice": 0, "gids": {"real": 32264, "effetive": 32264, "saved": 32264}, "ppid": 3064, "uids": {"real": 9182, "effetive": 9182, "saved": 0}, "SET_NPROC": "7", "ACTUAL_NPROC": "1", "HOSTNAME": "sh-18-12.int", "MAXMEMORY": "12", "SECONDS": "20"}, {"username": "vsochat", "create_time": 1558275530.21, "cpu_affinity": [2, 3, 6, 7, 8, 9, 10], "pid": 3068, "cpu_percent": 0.0, "num_ctx_switches": {"voluntary": 82, "involuntary": 3}, "name": "starter-suid", "cpu_times": {"user": 0.1, "system": 0.04, "children_user": 0.01, "children_system": 0.0}, "cpu_num": 7, "status": "sleeping", "cmdline": ["Singularity runtime parent"], "memory_percent": 0.013302107956979274, "ionice": {"ioclass": "IOPRIO_CLASS_NONE", "value": 0}, "num_threads": 7, "nice": 0, "gids": {"real": 32264, "effetive": 32264, "saved": 32264}, "ppid": 3064, "uids": {"real": 9182, "effetive": 9182, "saved": 0}, "SET_NPROC": "7", "ACTUAL_NPROC": "1", "HOSTNAME": "sh-18-12.int", "MAXMEMORY": "12", "SECONDS": "20"}, {"username": "vsochat", "create_time": 1558275530.21, "cpu_affinity": [2, 3, 6, 7, 8, 9, 10], "pid": 3068, "cpu_percent": 0.0, "num_ctx_switches": {"voluntary": 82, "involuntary": 3}, "name": "starter-suid", "cpu_times": {"user": 0.1, "system": 0.04, "children_user": 0.01, "children_system": 0.0}, "cpu_num": 7, "status": "sleeping", "cmdline": ["Singularity runtime parent"], "memory_percent": 0.013302107956979274, "ionice": {"ioclass": "IOPRIO_CLASS_NONE", "value": 0}, "num_threads": 7, "nice": 0, "gids": {"real": 32264, "effetive": 32264, "saved": 32264}, "ppid": 3064, "uids": {"real": 9182, "effetive": 9182, "saved": 0}, "SET_NPROC": "7", "ACTUAL_NPROC": "1", "HOSTNAME": "sh-18-12.int", "MAXMEMORY": "12", "SECONDS": "20"}, {"username": "vsochat", "create_time": 1558275530.21, "cpu_affinity": [2, 3, 6, 7, 8, 9, 10], "pid": 3068, "cpu_percent": 0.0, "num_ctx_switches": {"voluntary": 82, "involuntary": 3}, "name": "starter-suid", "cpu_times": {"user": 0.1, "system": 0.04, "children_user": 0.01, "children_system": 0.0}, "cpu_num": 7, "status": "sleeping", "cmdline": ["Singularity runtime parent"], "memory_percent": 0.013302107956979274, "ionice": {"ioclass": "IOPRIO_CLASS_NONE", "value": 0}, "num_threads": 7, "nice": 0, "gids": {"real": 32264, "effetive": 32264, "saved": 32264}, "ppid": 3064, "uids": {"real": 9182, "effetive": 9182, "saved": 0}, "SET_NPROC": "7", "ACTUAL_NPROC": "1", "HOSTNAME": "sh-18-12.int", "MAXMEMORY": "12", "SECONDS": "20"}, {"username": "vsochat", "create_time": 1558275530.21, "cpu_affinity": [2, 3, 6, 7, 8, 9, 10], "pid": 3068, "cpu_percent": 0.0, "num_ctx_switches": {"voluntary": 82, "involuntary": 3}, "name": "starter-suid", "cpu_times": {"user": 0.1, "system": 0.04, "children_user": 0.01, "children_system": 0.0}, "cpu_num": 7, "status": "sleeping", "cmdline": ["Singularity runtime parent"], "memory_percent": 0.013302107956979274, "ionice": {"ioclass": "IOPRIO_CLASS_NONE", "value": 0}, "num_threads": 7, "nice": 0, "gids": {"real": 32264, "effetive": 32264, "saved": 32264}, "ppid": 3064, "uids": {"real": 9182, "effetive": 9182, "saved": 0}, "SET_NPROC": "7", "ACTUAL_NPROC": "1", "HOSTNAME": "sh-18-12.int", "MAXMEMORY": "12", "SECONDS": "20"}, {"username": "vsochat", "create_time": 1558275530.21, "cpu_affinity": [2, 3, 6, 7, 8, 9, 10], "pid": 3068, "cpu_percent": 0.0, "num_ctx_switches": {"voluntary": 82, "involuntary": 3}, "name": "starter-suid", "cpu_times": {"user": 0.1, "system": 0.04, "children_user": 0.01, "children_system": 0.0}, "cpu_num": 7, "status": "sleeping", "cmdline": ["Singularity runtime parent"], "memory_percent": 0.013302107956979274, "ionice": {"ioclass": "IOPRIO_CLASS_NONE", "value": 0}, "num_threads": 7, "nice": 0, "gids": {"real": 32264, "effetive": 32264, "saved": 32264}, "ppid": 3064, "uids": {"real": 9182, "effetive": 9182, "saved": 0}, "SET_NPROC": "7", "ACTUAL_NPROC": "1", "HOSTNAME": "sh-18-12.int", "MAXMEMORY": "12", "SECONDS": "20"}, {"username": "vsochat", "create_time": 1558275530.21, "cpu_affinity": [2, 3, 6, 7, 8, 9, 10], "pid": 3068, "cpu_percent": 0.0, "num_ctx_switches": {"voluntary": 82, "involuntary": 3}, "name": "starter-suid", "cpu_times": {"user": 0.1, "system": 0.04, "children_user": 0.01, "children_system": 0.0}, "cpu_num": 7, "status": "sleeping", "cmdline": ["Singularity runtime parent"], "memory_percent": 0.013302107956979274, "ionice": {"ioclass": "IOPRIO_CLASS_NONE", "value": 0}, "num_threads": 7, "nice": 0, "gids": {"real": 32264, "effetive": 32264, "saved": 32264}, "ppid": 3064, "uids": {"real": 9182, "effetive": 9182, "saved": 0}, "SET_NPROC": "7", "ACTUAL_NPROC": "1", "HOSTNAME": "sh-18-12.int", "MAXMEMORY": "12", "SECONDS": "20"}, {"username": "vsochat", "create_time": 1558275530.21, "cpu_affinity": [2, 3, 6, 7, 8, 9, 10], "pid": 3068, "cpu_percent": 0.0, "num_ctx_switches": {"voluntary": 82, "involuntary": 3}, "name": "starter-suid", "cpu_times": {"user": 0.1, "system": 0.04, "children_user": 0.01, "children_system": 0.0}, "cpu_num": 7, "status": "sleeping", "cmdline": ["Singularity runtime parent"], "memory_percent": 0.013302107956979274, "ionice": {"ioclass": "IOPRIO_CLASS_NONE", "value": 0}, "num_threads": 7, "nice": 0, "gids": {"real": 32264, "effetive": 32264, "saved": 32264}, "ppid": 3064, "uids": {"real": 9182, "effetive": 9182, "saved": 0}, "SET_NPROC": "7", "ACTUAL_NPROC": "1", "HOSTNAME": "sh-18-12.int", "MAXMEMORY": "12", "SECONDS": "20"}]
