[{"cpu_percent": 0.0, "create_time": 1558275264.21, "cpu_affinity": [22, 23], "uids": {"real": 9182, "effetive": 9182, "saved": 9182}, "exe": "/usr/bin/singularity", "memory_full_info": {"rss": 1884160, "vms": 135876608, "shared": 1482752, "text": 20971520, "lib": 0, "data": 103727104, "dirty": 0, "uss": 1626112, "pss": 1634304, "swap": 0}, "gids": {"real": 32264, "effetive": 32264, "saved": 32264}, "num_fds": 3, "open_files": 0, "nice": 0, "name": "singularity", "num_threads": 1, "pid": 10137, "memory_percent": 0.001050712282132212, "connections": [], "num_ctx_switches": {"voluntary": 76, "involuntary": 7}, "username": "vsochat", "ppid": 10134, "io_counters": {"read_count": 9, "write_count": 0, "read_bytes": 6139904, "write_bytes": 0, "read_chars": 4564, "write_chars": 0}, "cmdline": ["singularity", "run", "docker://vanessa/watchme-mnist", "/home/users/vsochat/.watchme/mnist/data/watchme-mnist-cpu-iter2-proc30.png"], "cwd": "/scratch/users/vsochat", "cpu_times": {"user": 0.0, "system": 0.0, "children_user": 0.0, "children_system": 0.0}, "ionice": {"ioclass": "IOPRIO_CLASS_NONE", "value": 0}, "cpu_num": 22, "status": "disk-sleep", "SET_NPROC": "30", "ACTUAL_NPROC": "1", "HOSTNAME": "sh-107-26.int", "MAXMEMORY": "12", "SECONDS": "20"}, {"cpu_percent": 0.0, "create_time": 1558275264.21, "cpu_affinity": [22, 23], "uids": {"real": 9182, "effetive": 9182, "saved": 0}, "gids": {"real": 32264, "effetive": 32264, "saved": 32264}, "nice": 0, "name": "starter-suid", "num_threads": 7, "pid": 10137, "memory_percent": 0.004426838180921374, "num_ctx_switches": {"voluntary": 96, "involuntary": 41}, "username": "vsochat", "ppid": 10134, "cmdline": ["Singularity runtime parent"], "cpu_times": {"user": 0.06, "system": 0.03, "children_user": 0.0, "children_system": 0.0}, "ionice": {"ioclass": "IOPRIO_CLASS_NONE", "value": 0}, "cpu_num": 22, "status": "sleeping", "SET_NPROC": "30", "ACTUAL_NPROC": "1", "HOSTNAME": "sh-107-26.int", "MAXMEMORY": "12", "SECONDS": "20"}, {"cpu_percent": 0.0, "create_time": 1558275264.21, "cpu_affinity": [22, 23], "uids": {"real": 9182, "effetive": 9182, "saved": 0}, "gids": {"real": 32264, "effetive": 32264, "saved": 32264}, "nice": 0, "name": "starter-suid", "num_threads": 7, "pid": 10137, "memory_percent": 0.004426838180921374, "num_ctx_switches": {"voluntary": 96, "involuntary": 41}, "username": "vsochat", "ppid": 10134, "cmdline": ["Singularity runtime parent"], "cpu_times": {"user": 0.06, "system": 0.03, "children_user": 0.0, "children_system": 0.0}, "ionice": {"ioclass": "IOPRIO_CLASS_NONE", "value": 0}, "cpu_num": 22, "status": "sleeping", "SET_NPROC": "30", "ACTUAL_NPROC": "1", "HOSTNAME": "sh-107-26.int", "MAXMEMORY": "12", "SECONDS": "20"}, {"cpu_percent": 0.0, "create_time": 1558275264.21, "cpu_affinity": [22, 23], "uids": {"real": 9182, "effetive": 9182, "saved": 0}, "gids": {"real": 32264, "effetive": 32264, "saved": 32264}, "nice": 0, "name": "starter-suid", "num_threads": 7, "pid": 10137, "memory_percent": 0.004426838180921374, "num_ctx_switches": {"voluntary": 96, "involuntary": 41}, "username": "vsochat", "ppid": 10134, "cmdline": ["Singularity runtime parent"], "cpu_times": {"user": 0.06, "system": 0.03, "children_user": 0.0, "children_system": 0.0}, "ionice": {"ioclass": "IOPRIO_CLASS_NONE", "value": 0}, "cpu_num": 22, "status": "sleeping", "SET_NPROC": "30", "ACTUAL_NPROC": "1", "HOSTNAME": "sh-107-26.int", "MAXMEMORY": "12", "SECONDS": "20"}, {"cpu_percent": 0.0, "create_time": 1558275264.21, "cpu_affinity": [22, 23], "uids": {"real": 9182, "effetive": 9182, "saved": 0}, "gids": {"real": 32264, "effetive": 32264, "saved": 32264}, "nice": 0, "name": "starter-suid", "num_threads": 7, "pid": 10137, "memory_percent": 0.004426838180921374, "num_ctx_switches": {"voluntary": 96, "involuntary": 41}, "username": "vsochat", "ppid": 10134, "cmdline": ["Singularity runtime parent"], "cpu_times": {"user": 0.06, "system": 0.03, "children_user": 0.0, "children_system": 0.0}, "ionice": {"ioclass": "IOPRIO_CLASS_NONE", "value": 0}, "cpu_num": 22, "status": "sleeping", "SET_NPROC": "30", "ACTUAL_NPROC": "1", "HOSTNAME": "sh-107-26.int", "MAXMEMORY": "12", "SECONDS": "20"}, {"cpu_percent": 0.0, "create_time": 1558275264.21, "cpu_affinity": [22, 23], "uids": {"real": 9182, "effetive": 9182, "saved": 0}, "gids": {"real": 32264, "effetive": 32264, "saved": 32264}, "nice": 0, "name": "starter-suid", "num_threads": 7, "pid": 10137, "memory_percent": 0.004426838180921374, "num_ctx_switches": {"voluntary": 96, "involuntary": 41}, "username": "vsochat", "ppid": 10134, "cmdline": ["Singularity runtime parent"], "cpu_times": {"user": 0.06, "system": 0.03, "children_user": 0.0, "children_system": 0.0}, "ionice": {"ioclass": "IOPRIO_CLASS_NONE", "value": 0}, "cpu_num": 22, "status": "sleeping", "SET_NPROC": "30", "ACTUAL_NPROC": "1", "HOSTNAME": "sh-107-26.int", "MAXMEMORY": "12", "SECONDS": "20"}, {"cpu_percent": 0.0, "create_time": 1558275264.21, "cpu_affinity": [22, 23], "uids": {"real": 9182, "effetive": 9182, "saved": 0}, "gids": {"real": 32264, "effetive": 32264, "saved": 32264}, "nice": 0, "name": "starter-suid", "num_threads": 7, "pid": 10137, "memory_percent": 0.004426838180921374, "num_ctx_switches": {"voluntary": 96, "involuntary": 41}, "username": "vsochat", "ppid": 10134, "cmdline": ["Singularity runtime parent"], "cpu_times": {"user": 0.06, "system": 0.03, "children_user": 0.0, "children_system": 0.0}, "ionice": {"ioclass": "IOPRIO_CLASS_NONE", "value": 0}, "cpu_num": 22, "status": "sleeping", "SET_NPROC": "30", "ACTUAL_NPROC": "1", "HOSTNAME": "sh-107-26.int", "MAXMEMORY": "12", "SECONDS": "20"}, {"cpu_percent": 0.0, "create_time": 1558275264.21, "cpu_affinity": [22, 23], "uids": {"real": 9182, "effetive": 9182, "saved": 0}, "gids": {"real": 32264, "effetive": 32264, "saved": 32264}, "nice": 0, "name": "starter-suid", "num_threads": 7, "pid": 10137, "memory_percent": 0.004426838180921374, "num_ctx_switches": {"voluntary": 96, "involuntary": 41}, "username": "vsochat", "ppid": 10134, "cmdline": ["Singularity runtime parent"], "cpu_times": {"user": 0.06, "system": 0.03, "children_user": 0.0, "children_system": 0.0}, "ionice": {"ioclass": "IOPRIO_CLASS_NONE", "value": 0}, "cpu_num": 22, "status": "sleeping", "SET_NPROC": "30", "ACTUAL_NPROC": "1", "HOSTNAME": "sh-107-26.int", "MAXMEMORY": "12", "SECONDS": "20"}, {"cpu_percent": 0.0, "create_time": 1558275264.21, "cpu_affinity": [22, 23], "uids": {"real": 9182, "effetive": 9182, "saved": 0}, "gids": {"real": 32264, "effetive": 32264, "saved": 32264}, "nice": 0, "name": "starter-suid", "num_threads": 7, "pid": 10137, "memory_percent": 0.004426838180921374, "num_ctx_switches": {"voluntary": 96, "involuntary": 41}, "username": "vsochat", "ppid": 10134, "cmdline": ["Singularity runtime parent"], "cpu_times": {"user": 0.06, "system": 0.03, "children_user": 0.0, "children_system": 0.0}, "ionice": {"ioclass": "IOPRIO_CLASS_NONE", "value": 0}, "cpu_num": 22, "status": "sleeping", "SET_NPROC": "30", "ACTUAL_NPROC": "1", "HOSTNAME": "sh-107-26.int", "MAXMEMORY": "12", "SECONDS": "20"}, {"cpu_percent": 0.0, "create_time": 1558275264.21, "cpu_affinity": [22, 23], "uids": {"real": 9182, "effetive": 9182, "saved": 0}, "gids": {"real": 32264, "effetive": 32264, "saved": 32264}, "nice": 0, "name": "starter-suid", "num_threads": 7, "pid": 10137, "memory_percent": 0.004426838180921374, "num_ctx_switches": {"voluntary": 96, "involuntary": 41}, "username": "vsochat", "ppid": 10134, "cmdline": ["Singularity runtime parent"], "cpu_times": {"user": 0.06, "system": 0.03, "children_user": 0.0, "children_system": 0.0}, "ionice": {"ioclass": "IOPRIO_CLASS_NONE", "value": 0}, "cpu_num": 22, "status": "sleeping", "SET_NPROC": "30", "ACTUAL_NPROC": "1", "HOSTNAME": "sh-107-26.int", "MAXMEMORY": "12", "SECONDS": "20"}, {"cpu_percent": 0.0, "create_time": 1558275264.21, "cpu_affinity": [22, 23], "uids": {"real": 9182, "effetive": 9182, "saved": 0}, "gids": {"real": 32264, "effetive": 32264, "saved": 32264}, "nice": 0, "name": "starter-suid", "num_threads": 7, "pid": 10137, "memory_percent": 0.004426838180921374, "num_ctx_switches": {"voluntary": 96, "involuntary": 41}, "username": "vsochat", "ppid": 10134, "cmdline": ["Singularity runtime parent"], "cpu_times": {"user": 0.06, "system": 0.03, "children_user": 0.0, "children_system": 0.0}, "ionice": {"ioclass": "IOPRIO_CLASS_NONE", "value": 0}, "cpu_num": 22, "status": "sleeping", "SET_NPROC": "30", "ACTUAL_NPROC": "1", "HOSTNAME": "sh-107-26.int", "MAXMEMORY": "12", "SECONDS": "20"}, {"cpu_percent": 0.0, "create_time": 1558275264.21, "cpu_affinity": [22, 23], "uids": {"real": 9182, "effetive": 9182, "saved": 0}, "gids": {"real": 32264, "effetive": 32264, "saved": 32264}, "nice": 0, "name": "starter-suid", "num_threads": 7, "pid": 10137, "memory_percent": 0.004426838180921374, "num_ctx_switches": {"voluntary": 96, "involuntary": 41}, "username": "vsochat", "ppid": 10134, "cmdline": ["Singularity runtime parent"], "cpu_times": {"user": 0.06, "system": 0.03, "children_user": 0.0, "children_system": 0.0}, "ionice": {"ioclass": "IOPRIO_CLASS_NONE", "value": 0}, "cpu_num": 22, "status": "sleeping", "SET_NPROC": "30", "ACTUAL_NPROC": "1", "HOSTNAME": "sh-107-26.int", "MAXMEMORY": "12", "SECONDS": "20"}, {"cpu_percent": 0.0, "create_time": 1558275264.21, "cpu_affinity": [22, 23], "uids": {"real": 9182, "effetive": 9182, "saved": 0}, "gids": {"real": 32264, "effetive": 32264, "saved": 32264}, "nice": 0, "name": "starter-suid", "num_threads": 7, "pid": 10137, "memory_percent": 0.004426838180921374, "num_ctx_switches": {"voluntary": 96, "involuntary": 41}, "username": "vsochat", "ppid": 10134, "cmdline": ["Singularity runtime parent"], "cpu_times": {"user": 0.06, "system": 0.03, "children_user": 0.0, "children_system": 0.0}, "ionice": {"ioclass": "IOPRIO_CLASS_NONE", "value": 0}, "cpu_num": 22, "status": "sleeping", "SET_NPROC": "30", "ACTUAL_NPROC": "1", "HOSTNAME": "sh-107-26.int", "MAXMEMORY": "12", "SECONDS": "20"}, {"cpu_percent": 0.0, "create_time": 1558275264.21, "cpu_affinity": [22, 23], "uids": {"real": 9182, "effetive": 9182, "saved": 0}, "gids": {"real": 32264, "effetive": 32264, "saved": 32264}, "nice": 0, "name": "starter-suid", "num_threads": 7, "pid": 10137, "memory_percent": 0.004426838180921374, "num_ctx_switches": {"voluntary": 96, "involuntary": 41}, "username": "vsochat", "ppid": 10134, "cmdline": ["Singularity runtime parent"], "cpu_times": {"user": 0.06, "system": 0.03, "children_user": 0.0, "children_system": 0.0}, "ionice": {"ioclass": "IOPRIO_CLASS_NONE", "value": 0}, "cpu_num": 22, "status": "sleeping", "SET_NPROC": "30", "ACTUAL_NPROC": "1", "HOSTNAME": "sh-107-26.int", "MAXMEMORY": "12", "SECONDS": "20"}, {"cpu_percent": 0.0, "create_time": 1558275264.21, "cpu_affinity": [22, 23], "uids": {"real": 9182, "effetive": 9182, "saved": 0}, "gids": {"real": 32264, "effetive": 32264, "saved": 32264}, "nice": 0, "name": "starter-suid", "num_threads": 7, "pid": 10137, "memory_percent": 0.004426838180921374, "num_ctx_switches": {"voluntary": 96, "involuntary": 41}, "username": "vsochat", "ppid": 10134, "cmdline": ["Singularity runtime parent"], "cpu_times": {"user": 0.06, "system": 0.03, "children_user": 0.0, "children_system": 0.0}, "ionice": {"ioclass": "IOPRIO_CLASS_NONE", "value": 0}, "cpu_num": 22, "status": "sleeping", "SET_NPROC": "30", "ACTUAL_NPROC": "1", "HOSTNAME": "sh-107-26.int", "MAXMEMORY": "12", "SECONDS": "20"}, {"cpu_percent": 0.0, "create_time": 1558275264.21, "cpu_affinity": [22, 23], "uids": {"real": 9182, "effetive": 9182, "saved": 0}, "gids": {"real": 32264, "effetive": 32264, "saved": 32264}, "nice": 0, "name": "starter-suid", "num_threads": 7, "pid": 10137, "memory_percent": 0.004426838180921374, "num_ctx_switches": {"voluntary": 96, "involuntary": 41}, "username": "vsochat", "ppid": 10134, "cmdline": ["Singularity runtime parent"], "cpu_times": {"user": 0.06, "system": 0.03, "children_user": 0.0, "children_system": 0.0}, "ionice": {"ioclass": "IOPRIO_CLASS_NONE", "value": 0}, "cpu_num": 22, "status": "sleeping", "SET_NPROC": "30", "ACTUAL_NPROC": "1", "HOSTNAME": "sh-107-26.int", "MAXMEMORY": "12", "SECONDS": "20"}, {"cpu_percent": 0.0, "create_time": 1558275264.21, "cpu_affinity": [22, 23], "uids": {"real": 9182, "effetive": 9182, "saved": 0}, "gids": {"real": 32264, "effetive": 32264, "saved": 32264}, "nice": 0, "name": "starter-suid", "num_threads": 7, "pid": 10137, "memory_percent": 0.004426838180921374, "num_ctx_switches": {"voluntary": 96, "involuntary": 41}, "username": "vsochat", "ppid": 10134, "cmdline": ["Singularity runtime parent"], "cpu_times": {"user": 0.06, "system": 0.03, "children_user": 0.0, "children_system": 0.0}, "ionice": {"ioclass": "IOPRIO_CLASS_NONE", "value": 0}, "cpu_num": 22, "status": "sleeping", "SET_NPROC": "30", "ACTUAL_NPROC": "1", "HOSTNAME": "sh-107-26.int", "MAXMEMORY": "12", "SECONDS": "20"}, {"cpu_percent": 0.0, "create_time": 1558275264.21, "cpu_affinity": [22, 23], "uids": {"real": 9182, "effetive": 9182, "saved": 0}, "gids": {"real": 32264, "effetive": 32264, "saved": 32264}, "nice": 0, "name": "starter-suid", "num_threads": 7, "pid": 10137, "memory_percent": 0.004426838180921374, "num_ctx_switches": {"voluntary": 96, "involuntary": 41}, "username": "vsochat", "ppid": 10134, "cmdline": ["Singularity runtime parent"], "cpu_times": {"user": 0.06, "system": 0.03, "children_user": 0.0, "children_system": 0.0}, "ionice": {"ioclass": "IOPRIO_CLASS_NONE", "value": 0}, "cpu_num": 22, "status": "sleeping", "SET_NPROC": "30", "ACTUAL_NPROC": "1", "HOSTNAME": "sh-107-26.int", "MAXMEMORY": "12", "SECONDS": "20"}, {"cpu_percent": 0.0, "create_time": 1558275264.21, "cpu_affinity": [22, 23], "uids": {"real": 9182, "effetive": 9182, "saved": 0}, "gids": {"real": 32264, "effetive": 32264, "saved": 32264}, "nice": 0, "name": "starter-suid", "num_threads": 7, "pid": 10137, "memory_percent": 0.004426838180921374, "num_ctx_switches": {"voluntary": 96, "involuntary": 41}, "username": "vsochat", "ppid": 10134, "cmdline": ["Singularity runtime parent"], "cpu_times": {"user": 0.06, "system": 0.03, "children_user": 0.0, "children_system": 0.0}, "ionice": {"ioclass": "IOPRIO_CLASS_NONE", "value": 0}, "cpu_num": 22, "status": "sleeping", "SET_NPROC": "30", "ACTUAL_NPROC": "1", "HOSTNAME": "sh-107-26.int", "MAXMEMORY": "12", "SECONDS": "20"}, {"cpu_percent": 0.0, "create_time": 1558275264.21, "cpu_affinity": [22, 23], "uids": {"real": 9182, "effetive": 9182, "saved": 0}, "gids": {"real": 32264, "effetive": 32264, "saved": 32264}, "nice": 0, "name": "starter-suid", "num_threads": 7, "pid": 10137, "memory_percent": 0.004428874445034033, "num_ctx_switches": {"voluntary": 96, "involuntary": 41}, "username": "vsochat", "ppid": 10134, "cmdline": ["Singularity runtime parent"], "cpu_times": {"user": 0.06, "system": 0.03, "children_user": 0.0, "children_system": 0.0}, "ionice": {"ioclass": "IOPRIO_CLASS_NONE", "value": 0}, "cpu_num": 22, "status": "sleeping", "SET_NPROC": "30", "ACTUAL_NPROC": "1", "HOSTNAME": "sh-107-26.int", "MAXMEMORY": "12", "SECONDS": "20"}, {"cpu_percent": 0.0, "create_time": 1558275264.21, "cpu_affinity": [22, 23], "uids": {"real": 9182, "effetive": 9182, "saved": 0}, "gids": {"real": 32264, "effetive": 32264, "saved": 32264}, "nice": 0, "name": "starter-suid", "num_threads": 7, "pid": 10137, "memory_percent": 0.004428874445034033, "num_ctx_switches": {"voluntary": 96, "involuntary": 41}, "username": "vsochat", "ppid": 10134, "cmdline": ["Singularity runtime parent"], "cpu_times": {"user": 0.06, "system": 0.03, "children_user": 0.0, "children_system": 0.0}, "ionice": {"ioclass": "IOPRIO_CLASS_NONE", "value": 0}, "cpu_num": 22, "status": "sleeping", "SET_NPROC": "30", "ACTUAL_NPROC": "1", "HOSTNAME": "sh-107-26.int", "MAXMEMORY": "12", "SECONDS": "20"}, {"cpu_percent": 0.0, "create_time": 1558275264.21, "cpu_affinity": [22, 23], "uids": {"real": 9182, "effetive": 9182, "saved": 0}, "gids": {"real": 32264, "effetive": 32264, "saved": 32264}, "nice": 0, "name": "starter-suid", "num_threads": 7, "pid": 10137, "memory_percent": 0.004428874445034033, "num_ctx_switches": {"voluntary": 96, "involuntary": 41}, "username": "vsochat", "ppid": 10134, "cmdline": ["Singularity runtime parent"], "cpu_times": {"user": 0.06, "system": 0.03, "children_user": 0.0, "children_system": 0.0}, "ionice": {"ioclass": "IOPRIO_CLASS_NONE", "value": 0}, "cpu_num": 22, "status": "sleeping", "SET_NPROC": "30", "ACTUAL_NPROC": "1", "HOSTNAME": "sh-107-26.int", "MAXMEMORY": "12", "SECONDS": "20"}, {"cpu_percent": 0.0, "create_time": 1558275264.21, "cpu_affinity": [22, 23], "uids": {"real": 9182, "effetive": 9182, "saved": 0}, "gids": {"real": 32264, "effetive": 32264, "saved": 32264}, "nice": 0, "name": "starter-suid", "num_threads": 7, "pid": 10137, "memory_percent": 0.004428874445034033, "num_ctx_switches": {"voluntary": 96, "involuntary": 41}, "username": "vsochat", "ppid": 10134, "cmdline": ["Singularity runtime parent"], "cpu_times": {"user": 0.06, "system": 0.03, "children_user": 0.0, "children_system": 0.0}, "ionice": {"ioclass": "IOPRIO_CLASS_NONE", "value": 0}, "cpu_num": 22, "status": "sleeping", "SET_NPROC": "30", "ACTUAL_NPROC": "1", "HOSTNAME": "sh-107-26.int", "MAXMEMORY": "12", "SECONDS": "20"}, {"cpu_percent": 0.0, "create_time": 1558275264.21, "cpu_affinity": [22, 23], "uids": {"real": 9182, "effetive": 9182, "saved": 0}, "gids": {"real": 32264, "effetive": 32264, "saved": 32264}, "nice": 0, "name": "starter-suid", "num_threads": 7, "pid": 10137, "memory_percent": 0.004428874445034033, "num_ctx_switches": {"voluntary": 96, "involuntary": 41}, "username": "vsochat", "ppid": 10134, "cmdline": ["Singularity runtime parent"], "cpu_times": {"user": 0.06, "system": 0.03, "children_user": 0.0, "children_system": 0.0}, "ionice": {"ioclass": "IOPRIO_CLASS_NONE", "value": 0}, "cpu_num": 22, "status": "sleeping", "SET_NPROC": "30", "ACTUAL_NPROC": "1", "HOSTNAME": "sh-107-26.int", "MAXMEMORY": "12", "SECONDS": "20"}, {"cpu_percent": 0.0, "create_time": 1558275264.21, "cpu_affinity": [22, 23], "uids": {"real": 9182, "effetive": 9182, "saved": 0}, "gids": {"real": 32264, "effetive": 32264, "saved": 32264}, "nice": 0, "name": "starter-suid", "num_threads": 7, "pid": 10137, "memory_percent": 0.004428874445034033, "num_ctx_switches": {"voluntary": 96, "involuntary": 41}, "username": "vsochat", "ppid": 10134, "cmdline": ["Singularity runtime parent"], "cpu_times": {"user": 0.06, "system": 0.03, "children_user": 0.0, "children_system": 0.0}, "ionice": {"ioclass": "IOPRIO_CLASS_NONE", "value": 0}, "cpu_num": 22, "status": "sleeping", "SET_NPROC": "30", "ACTUAL_NPROC": "1", "HOSTNAME": "sh-107-26.int", "MAXMEMORY": "12", "SECONDS": "20"}, {"cpu_percent": 0.0, "create_time": 1558275264.21, "cpu_affinity": [22, 23], "uids": {"real": 9182, "effetive": 9182, "saved": 0}, "gids": {"real": 32264, "effetive": 32264, "saved": 32264}, "nice": 0, "name": "starter-suid", "num_threads": 7, "pid": 10137, "memory_percent": 0.004428874445034033, "num_ctx_switches": {"voluntary": 96, "involuntary": 41}, "username": "vsochat", "ppid": 10134, "cmdline": ["Singularity runtime parent"], "cpu_times": {"user": 0.06, "system": 0.03, "children_user": 0.0, "children_system": 0.0}, "ionice": {"ioclass": "IOPRIO_CLASS_NONE", "value": 0}, "cpu_num": 22, "status": "sleeping", "SET_NPROC": "30", "ACTUAL_NPROC": "1", "HOSTNAME": "sh-107-26.int", "MAXMEMORY": "12", "SECONDS": "20"}, {"cpu_percent": 0.0, "create_time": 1558275264.21, "cpu_affinity": [22, 23], "uids": {"real": 9182, "effetive": 9182, "saved": 0}, "gids": {"real": 32264, "effetive": 32264, "saved": 32264}, "nice": 0, "name": "starter-suid", "num_threads": 7, "pid": 10137, "memory_percent": 0.004428874445034033, "num_ctx_switches": {"voluntary": 96, "involuntary": 41}, "username": "vsochat", "ppid": 10134, "cmdline": ["Singularity runtime parent"], "cpu_times": {"user": 0.06, "system": 0.03, "children_user": 0.0, "children_system": 0.0}, "ionice": {"ioclass": "IOPRIO_CLASS_NONE", "value": 0}, "cpu_num": 22, "status": "sleeping", "SET_NPROC": "30", "ACTUAL_NPROC": "1", "HOSTNAME": "sh-107-26.int", "MAXMEMORY": "12", "SECONDS": "20"}, {"cpu_percent": 0.0, "create_time": 1558275264.21, "cpu_affinity": [22, 23], "uids": {"real": 9182, "effetive": 9182, "saved": 0}, "gids": {"real": 32264, "effetive": 32264, "saved": 32264}, "nice": 0, "name": "starter-suid", "num_threads": 7, "pid": 10137, "memory_percent": 0.004428874445034033, "num_ctx_switches": {"voluntary": 96, "involuntary": 41}, "username": "vsochat", "ppid": 10134, "cmdline": ["Singularity runtime parent"], "cpu_times": {"user": 0.06, "system": 0.03, "children_user": 0.0, "children_system": 0.0}, "ionice": {"ioclass": "IOPRIO_CLASS_NONE", "value": 0}, "cpu_num": 22, "status": "sleeping", "SET_NPROC": "30", "ACTUAL_NPROC": "1", "HOSTNAME": "sh-107-26.int", "MAXMEMORY": "12", "SECONDS": "20"}, {"cpu_percent": 0.0, "create_time": 1558275264.21, "cpu_affinity": [22, 23], "uids": {"real": 9182, "effetive": 9182, "saved": 0}, "gids": {"real": 32264, "effetive": 32264, "saved": 32264}, "nice": 0, "name": "starter-suid", "num_threads": 7, "pid": 10137, "memory_percent": 0.004428874445034033, "num_ctx_switches": {"voluntary": 96, "involuntary": 41}, "username": "vsochat", "ppid": 10134, "cmdline": ["Singularity runtime parent"], "cpu_times": {"user": 0.06, "system": 0.03, "children_user": 0.0, "children_system": 0.0}, "ionice": {"ioclass": "IOPRIO_CLASS_NONE", "value": 0}, "cpu_num": 22, "status": "sleeping", "SET_NPROC": "30", "ACTUAL_NPROC": "1", "HOSTNAME": "sh-107-26.int", "MAXMEMORY": "12", "SECONDS": "20"}, {"cpu_percent": 0.0, "create_time": 1558275264.21, "cpu_affinity": [22, 23], "uids": {"real": 9182, "effetive": 9182, "saved": 0}, "gids": {"real": 32264, "effetive": 32264, "saved": 32264}, "nice": 0, "name": "starter-suid", "num_threads": 7, "pid": 10137, "memory_percent": 0.004428874445034033, "num_ctx_switches": {"voluntary": 96, "involuntary": 41}, "username": "vsochat", "ppid": 10134, "cmdline": ["Singularity runtime parent"], "cpu_times": {"user": 0.06, "system": 0.03, "children_user": 0.0, "children_system": 0.0}, "ionice": {"ioclass": "IOPRIO_CLASS_NONE", "value": 0}, "cpu_num": 22, "status": "sleeping", "SET_NPROC": "30", "ACTUAL_NPROC": "1", "HOSTNAME": "sh-107-26.int", "MAXMEMORY": "12", "SECONDS": "20"}, {"cpu_percent": 0.0, "create_time": 1558275264.21, "cpu_affinity": [22, 23], "uids": {"real": 9182, "effetive": 9182, "saved": 0}, "gids": {"real": 32264, "effetive": 32264, "saved": 32264}, "nice": 0, "name": "starter-suid", "num_threads": 7, "pid": 10137, "memory_percent": 0.004428874445034033, "num_ctx_switches": {"voluntary": 96, "involuntary": 41}, "username": "vsochat", "ppid": 10134, "cmdline": ["Singularity runtime parent"], "cpu_times": {"user": 0.06, "system": 0.03, "children_user": 0.0, "children_system": 0.0}, "ionice": {"ioclass": "IOPRIO_CLASS_NONE", "value": 0}, "cpu_num": 22, "status": "sleeping", "SET_NPROC": "30", "ACTUAL_NPROC": "1", "HOSTNAME": "sh-107-26.int", "MAXMEMORY": "12", "SECONDS": "20"}, {"cpu_percent": 0.0, "create_time": 1558275264.21, "cpu_affinity": [22, 23], "uids": {"real": 9182, "effetive": 9182, "saved": 0}, "gids": {"real": 32264, "effetive": 32264, "saved": 32264}, "nice": 0, "name": "starter-suid", "num_threads": 7, "pid": 10137, "memory_percent": 0.004428874445034033, "num_ctx_switches": {"voluntary": 96, "involuntary": 41}, "username": "vsochat", "ppid": 10134, "cmdline": ["Singularity runtime parent"], "cpu_times": {"user": 0.06, "system": 0.03, "children_user": 0.0, "children_system": 0.0}, "ionice": {"ioclass": "IOPRIO_CLASS_NONE", "value": 0}, "cpu_num": 22, "status": "sleeping", "SET_NPROC": "30", "ACTUAL_NPROC": "1", "HOSTNAME": "sh-107-26.int", "MAXMEMORY": "12", "SECONDS": "20"}, {"cpu_percent": 0.0, "create_time": 1558275264.21, "cpu_affinity": [22, 23], "uids": {"real": 9182, "effetive": 9182, "saved": 0}, "gids": {"real": 32264, "effetive": 32264, "saved": 32264}, "nice": 0, "name": "starter-suid", "num_threads": 7, "pid": 10137, "memory_percent": 0.004428874445034033, "num_ctx_switches": {"voluntary": 96, "involuntary": 41}, "username": "vsochat", "ppid": 10134, "cmdline": ["Singularity runtime parent"], "cpu_times": {"user": 0.06, "system": 0.03, "children_user": 0.0, "children_system": 0.0}, "ionice": {"ioclass": "IOPRIO_CLASS_NONE", "value": 0}, "cpu_num": 22, "status": "sleeping", "SET_NPROC": "30", "ACTUAL_NPROC": "1", "HOSTNAME": "sh-107-26.int", "MAXMEMORY": "12", "SECONDS": "20"}, {"cpu_percent": 0.0, "create_time": 1558275264.21, "cpu_affinity": [22, 23], "uids": {"real": 9182, "effetive": 9182, "saved": 0}, "gids": {"real": 32264, "effetive": 32264, "saved": 32264}, "nice": 0, "name": "starter-suid", "num_threads": 7, "pid": 10137, "memory_percent": 0.004428874445034033, "num_ctx_switches": {"voluntary": 96, "involuntary": 41}, "username": "vsochat", "ppid": 10134, "cmdline": ["Singularity runtime parent"], "cpu_times": {"user": 0.06, "system": 0.03, "children_user": 0.0, "children_system": 0.0}, "ionice": {"ioclass": "IOPRIO_CLASS_NONE", "value": 0}, "cpu_num": 22, "status": "sleeping", "SET_NPROC": "30", "ACTUAL_NPROC": "1", "HOSTNAME": "sh-107-26.int", "MAXMEMORY": "12", "SECONDS": "20"}, {"cpu_percent": 0.0, "create_time": 1558275264.21, "cpu_affinity": [22, 23], "uids": {"real": 9182, "effetive": 9182, "saved": 0}, "gids": {"real": 32264, "effetive": 32264, "saved": 32264}, "nice": 0, "name": "starter-suid", "num_threads": 7, "pid": 10137, "memory_percent": 0.004428874445034033, "num_ctx_switches": {"voluntary": 96, "involuntary": 41}, "username": "vsochat", "ppid": 10134, "cmdline": ["Singularity runtime parent"], "cpu_times": {"user": 0.06, "system": 0.03, "children_user": 0.0, "children_system": 0.0}, "ionice": {"ioclass": "IOPRIO_CLASS_NONE", "value": 0}, "cpu_num": 22, "status": "sleeping", "SET_NPROC": "30", "ACTUAL_NPROC": "1", "HOSTNAME": "sh-107-26.int", "MAXMEMORY": "12", "SECONDS": "20"}, {"cpu_percent": 0.0, "create_time": 1558275264.21, "cpu_affinity": [22, 23], "uids": {"real": 9182, "effetive": 9182, "saved": 0}, "gids": {"real": 32264, "effetive": 32264, "saved": 32264}, "nice": 0, "name": "starter-suid", "num_threads": 7, "pid": 10137, "memory_percent": 0.004428874445034033, "num_ctx_switches": {"voluntary": 96, "involuntary": 41}, "username": "vsochat", "ppid": 10134, "cmdline": ["Singularity runtime parent"], "cpu_times": {"user": 0.06, "system": 0.03, "children_user": 0.0, "children_system": 0.0}, "ionice": {"ioclass": "IOPRIO_CLASS_NONE", "value": 0}, "cpu_num": 22, "status": "sleeping", "SET_NPROC": "30", "ACTUAL_NPROC": "1", "HOSTNAME": "sh-107-26.int", "MAXMEMORY": "12", "SECONDS": "20"}, {"cpu_percent": 0.0, "create_time": 1558275264.21, "cpu_affinity": [22, 23], "uids": {"real": 9182, "effetive": 9182, "saved": 0}, "gids": {"real": 32264, "effetive": 32264, "saved": 32264}, "nice": 0, "name": "starter-suid", "num_threads": 7, "pid": 10137, "memory_percent": 0.004428874445034033, "num_ctx_switches": {"voluntary": 96, "involuntary": 41}, "username": "vsochat", "ppid": 10134, "cmdline": ["Singularity runtime parent"], "cpu_times": {"user": 0.06, "system": 0.03, "children_user": 0.0, "children_system": 0.0}, "ionice": {"ioclass": "IOPRIO_CLASS_NONE", "value": 0}, "cpu_num": 22, "status": "sleeping", "SET_NPROC": "30", "ACTUAL_NPROC": "1", "HOSTNAME": "sh-107-26.int", "MAXMEMORY": "12", "SECONDS": "20"}, {"cpu_percent": 0.0, "create_time": 1558275264.21, "cpu_affinity": [22, 23], "uids": {"real": 9182, "effetive": 9182, "saved": 0}, "gids": {"real": 32264, "effetive": 32264, "saved": 32264}, "nice": 0, "name": "starter-suid", "num_threads": 7, "pid": 10137, "memory_percent": 0.004428874445034033, "num_ctx_switches": {"voluntary": 96, "involuntary": 41}, "username": "vsochat", "ppid": 10134, "cmdline": ["Singularity runtime parent"], "cpu_times": {"user": 0.06, "system": 0.03, "children_user": 0.0, "children_system": 0.0}, "ionice": {"ioclass": "IOPRIO_CLASS_NONE", "value": 0}, "cpu_num": 22, "status": "sleeping", "SET_NPROC": "30", "ACTUAL_NPROC": "1", "HOSTNAME": "sh-107-26.int", "MAXMEMORY": "12", "SECONDS": "20"}, {"cpu_percent": 0.0, "create_time": 1558275264.21, "cpu_affinity": [22, 23], "uids": {"real": 9182, "effetive": 9182, "saved": 0}, "gids": {"real": 32264, "effetive": 32264, "saved": 32264}, "nice": 0, "name": "starter-suid", "num_threads": 7, "pid": 10137, "memory_percent": 0.004428874445034033, "num_ctx_switches": {"voluntary": 96, "involuntary": 41}, "username": "vsochat", "ppid": 10134, "cmdline": ["Singularity runtime parent"], "cpu_times": {"user": 0.06, "system": 0.03, "children_user": 0.0, "children_system": 0.0}, "ionice": {"ioclass": "IOPRIO_CLASS_NONE", "value": 0}, "cpu_num": 22, "status": "sleeping", "SET_NPROC": "30", "ACTUAL_NPROC": "1", "HOSTNAME": "sh-107-26.int", "MAXMEMORY": "12", "SECONDS": "20"}, {"cpu_percent": 0.0, "create_time": 1558275264.21, "cpu_affinity": [22, 23], "uids": {"real": 9182, "effetive": 9182, "saved": 0}, "gids": {"real": 32264, "effetive": 32264, "saved": 32264}, "nice": 0, "name": "starter-suid", "num_threads": 7, "pid": 10137, "memory_percent": 0.004428874445034033, "num_ctx_switches": {"voluntary": 96, "involuntary": 41}, "username": "vsochat", "ppid": 10134, "cmdline": ["Singularity runtime parent"], "cpu_times": {"user": 0.06, "system": 0.03, "children_user": 0.0, "children_system": 0.0}, "ionice": {"ioclass": "IOPRIO_CLASS_NONE", "value": 0}, "cpu_num": 22, "status": "sleeping", "SET_NPROC": "30", "ACTUAL_NPROC": "1", "HOSTNAME": "sh-107-26.int", "MAXMEMORY": "12", "SECONDS": "20"}]
