[{"memory_percent": 0.01764664856156322, "pid": 39238, "cpu_num": 0, "open_files": 0, "ppid": 39234, "ionice": {"ioclass": "IOPRIO_CLASS_NONE", "value": 0}, "username": "vsochat", "io_counters": {"read_count": 25, "write_count": 0, "read_bytes": 3063808, "write_bytes": 0, "read_chars": 13437, "write_chars": 0}, "connections": [{"fd": 3, "family": "AddressFamily.AF_INET", "type": "SocketKind.SOCK_STREAM", "laddr_ip": "10.10.7.27", "laddr_port": 57642, "raddr": ["52.22.67.152", 443], "status": "SYN_SENT"}], "cpu_times": {"user": 0.01, "system": 0.01, "children_user": 0.0, "children_system": 0.0}, "gids": {"real": 32264, "effetive": 32264, "saved": 32264}, "cmdline": ["singularity", "run", "docker://vanessa/watchme-mnist", "/home/users/vsochat/.watchme/mnist/data/watchme-mnist-cpu-iter1-proc15.png"], "num_threads": 11, "exe": "/usr/bin/singularity", "cpu_percent": 0.0, "name": "singularity", "nice": 0, "uids": {"real": 9182, "effetive": 9182, "saved": 9182}, "cwd": "/scratch/users/vsochat", "cpu_affinity": [0, 1, 2, 3, 4, 5, 6, 7, 14], "memory_full_info": {"rss": 11845632, "vms": 490360832, "shared": 6766592, "text": 20971520, "lib": 0, "data": 457203712, "dirty": 0, "uss": 11681792, "pss": 11696128, "swap": 0}, "status": "sleeping", "num_ctx_switches": {"voluntary": 114, "involuntary": 1}, "num_fds": 5, "create_time": 1558275214.15, "SET_NPROC": "15", "ACTUAL_NPROC": "1", "HOSTNAME": "sh-07-27.int", "MAXMEMORY": "12", "SECONDS": "20"}, {"memory_percent": 0.01361330322989196, "pid": 39238, "cpu_num": 6, "ppid": 39234, "ionice": {"ioclass": "IOPRIO_CLASS_NONE", "value": 0}, "username": "vsochat", "cpu_times": {"user": 0.12, "system": 0.04, "children_user": 0.01, "children_system": 0.0}, "gids": {"real": 32264, "effetive": 32264, "saved": 32264}, "cmdline": ["Singularity runtime parent"], "num_threads": 7, "cpu_percent": 0.0, "name": "starter-suid", "nice": 0, "uids": {"real": 9182, "effetive": 9182, "saved": 0}, "cpu_affinity": [0, 1, 2, 3, 4, 5, 6, 7, 14], "status": "sleeping", "num_ctx_switches": {"voluntary": 83, "involuntary": 8}, "create_time": 1558275214.15, "SET_NPROC": "15", "ACTUAL_NPROC": "1", "HOSTNAME": "sh-07-27.int", "MAXMEMORY": "12", "SECONDS": "20"}, {"memory_percent": 0.01361330322989196, "pid": 39238, "cpu_num": 6, "ppid": 39234, "ionice": {"ioclass": "IOPRIO_CLASS_NONE", "value": 0}, "username": "vsochat", "cpu_times": {"user": 0.12, "system": 0.04, "children_user": 0.01, "children_system": 0.0}, "gids": {"real": 32264, "effetive": 32264, "saved": 32264}, "cmdline": ["Singularity runtime parent"], "num_threads": 7, "cpu_percent": 0.0, "name": "starter-suid", "nice": 0, "uids": {"real": 9182, "effetive": 9182, "saved": 0}, "cpu_affinity": [0, 1, 2, 3, 4, 5, 6, 7, 14], "status": "sleeping", "num_ctx_switches": {"voluntary": 83, "involuntary": 8}, "create_time": 1558275214.15, "SET_NPROC": "15", "ACTUAL_NPROC": "1", "HOSTNAME": "sh-07-27.int", "MAXMEMORY": "12", "SECONDS": "20"}, {"memory_percent": 0.01361330322989196, "pid": 39238, "cpu_num": 6, "ppid": 39234, "ionice": {"ioclass": "IOPRIO_CLASS_NONE", "value": 0}, "username": "vsochat", "cpu_times": {"user": 0.12, "system": 0.04, "children_user": 0.01, "children_system": 0.0}, "gids": {"real": 32264, "effetive": 32264, "saved": 32264}, "cmdline": ["Singularity runtime parent"], "num_threads": 7, "cpu_percent": 0.0, "name": "starter-suid", "nice": 0, "uids": {"real": 9182, "effetive": 9182, "saved": 0}, "cpu_affinity": [0, 1, 2, 3, 4, 5, 6, 7, 14], "status": "sleeping", "num_ctx_switches": {"voluntary": 83, "involuntary": 8}, "create_time": 1558275214.15, "SET_NPROC": "15", "ACTUAL_NPROC": "1", "HOSTNAME": "sh-07-27.int", "MAXMEMORY": "12", "SECONDS": "20"}, {"memory_percent": 0.01361330322989196, "pid": 39238, "cpu_num": 6, "ppid": 39234, "ionice": {"ioclass": "IOPRIO_CLASS_NONE", "value": 0}, "username": "vsochat", "cpu_times": {"user": 0.12, "system": 0.04, "children_user": 0.01, "children_system": 0.0}, "gids": {"real": 32264, "effetive": 32264, "saved": 32264}, "cmdline": ["Singularity runtime parent"], "num_threads": 7, "cpu_percent": 0.0, "name": "starter-suid", "nice": 0, "uids": {"real": 9182, "effetive": 9182, "saved": 0}, "cpu_affinity": [0, 1, 2, 3, 4, 5, 6, 7, 14], "status": "sleeping", "num_ctx_switches": {"voluntary": 83, "involuntary": 8}, "create_time": 1558275214.15, "SET_NPROC": "15", "ACTUAL_NPROC": "1", "HOSTNAME": "sh-07-27.int", "MAXMEMORY": "12", "SECONDS": "20"}, {"memory_percent": 0.01361330322989196, "pid": 39238, "cpu_num": 6, "ppid": 39234, "ionice": {"ioclass": "IOPRIO_CLASS_NONE", "value": 0}, "username": "vsochat", "cpu_times": {"user": 0.12, "system": 0.04, "children_user": 0.01, "children_system": 0.0}, "gids": {"real": 32264, "effetive": 32264, "saved": 32264}, "cmdline": ["Singularity runtime parent"], "num_threads": 7, "cpu_percent": 0.0, "name": "starter-suid", "nice": 0, "uids": {"real": 9182, "effetive": 9182, "saved": 0}, "cpu_affinity": [0, 1, 2, 3, 4, 5, 6, 7, 14], "status": "sleeping", "num_ctx_switches": {"voluntary": 83, "involuntary": 8}, "create_time": 1558275214.15, "SET_NPROC": "15", "ACTUAL_NPROC": "1", "HOSTNAME": "sh-07-27.int", "MAXMEMORY": "12", "SECONDS": "20"}, {"memory_percent": 0.01361330322989196, "pid": 39238, "cpu_num": 6, "ppid": 39234, "ionice": {"ioclass": "IOPRIO_CLASS_NONE", "value": 0}, "username": "vsochat", "cpu_times": {"user": 0.12, "system": 0.04, "children_user": 0.01, "children_system": 0.0}, "gids": {"real": 32264, "effetive": 32264, "saved": 32264}, "cmdline": ["Singularity runtime parent"], "num_threads": 7, "cpu_percent": 0.0, "name": "starter-suid", "nice": 0, "uids": {"real": 9182, "effetive": 9182, "saved": 0}, "cpu_affinity": [0, 1, 2, 3, 4, 5, 6, 7, 14], "status": "sleeping", "num_ctx_switches": {"voluntary": 83, "involuntary": 8}, "create_time": 1558275214.15, "SET_NPROC": "15", "ACTUAL_NPROC": "1", "HOSTNAME": "sh-07-27.int", "MAXMEMORY": "12", "SECONDS": "20"}, {"memory_percent": 0.01361330322989196, "pid": 39238, "cpu_num": 6, "ppid": 39234, "ionice": {"ioclass": "IOPRIO_CLASS_NONE", "value": 0}, "username": "vsochat", "cpu_times": {"user": 0.12, "system": 0.04, "children_user": 0.01, "children_system": 0.0}, "gids": {"real": 32264, "effetive": 32264, "saved": 32264}, "cmdline": ["Singularity runtime parent"], "num_threads": 7, "cpu_percent": 0.0, "name": "starter-suid", "nice": 0, "uids": {"real": 9182, "effetive": 9182, "saved": 0}, "cpu_affinity": [0, 1, 2, 3, 4, 5, 6, 7, 14], "status": "sleeping", "num_ctx_switches": {"voluntary": 83, "involuntary": 8}, "create_time": 1558275214.15, "SET_NPROC": "15", "ACTUAL_NPROC": "1", "HOSTNAME": "sh-07-27.int", "MAXMEMORY": "12", "SECONDS": "20"}, {"memory_percent": 0.01361330322989196, "pid": 39238, "cpu_num": 6, "ppid": 39234, "ionice": {"ioclass": "IOPRIO_CLASS_NONE", "value": 0}, "username": "vsochat", "cpu_times": {"user": 0.12, "system": 0.04, "children_user": 0.01, "children_system": 0.0}, "gids": {"real": 32264, "effetive": 32264, "saved": 32264}, "cmdline": ["Singularity runtime parent"], "num_threads": 7, "cpu_percent": 0.0, "name": "starter-suid", "nice": 0, "uids": {"real": 9182, "effetive": 9182, "saved": 0}, "cpu_affinity": [0, 1, 2, 3, 4, 5, 6, 7, 14], "status": "sleeping", "num_ctx_switches": {"voluntary": 83, "involuntary": 8}, "create_time": 1558275214.15, "SET_NPROC": "15", "ACTUAL_NPROC": "1", "HOSTNAME": "sh-07-27.int", "MAXMEMORY": "12", "SECONDS": "20"}, {"memory_percent": 0.01361330322989196, "pid": 39238, "cpu_num": 6, "ppid": 39234, "ionice": {"ioclass": "IOPRIO_CLASS_NONE", "value": 0}, "username": "vsochat", "cpu_times": {"user": 0.12, "system": 0.04, "children_user": 0.01, "children_system": 0.0}, "gids": {"real": 32264, "effetive": 32264, "saved": 32264}, "cmdline": ["Singularity runtime parent"], "num_threads": 7, "cpu_percent": 0.0, "name": "starter-suid", "nice": 0, "uids": {"real": 9182, "effetive": 9182, "saved": 0}, "cpu_affinity": [0, 1, 2, 3, 4, 5, 6, 7, 14], "status": "sleeping", "num_ctx_switches": {"voluntary": 83, "involuntary": 8}, "create_time": 1558275214.15, "SET_NPROC": "15", "ACTUAL_NPROC": "1", "HOSTNAME": "sh-07-27.int", "MAXMEMORY": "12", "SECONDS": "20"}, {"memory_percent": 0.01361330322989196, "pid": 39238, "cpu_num": 6, "ppid": 39234, "ionice": {"ioclass": "IOPRIO_CLASS_NONE", "value": 0}, "username": "vsochat", "cpu_times": {"user": 0.12, "system": 0.04, "children_user": 0.01, "children_system": 0.0}, "gids": {"real": 32264, "effetive": 32264, "saved": 32264}, "cmdline": ["Singularity runtime parent"], "num_threads": 7, "cpu_percent": 0.0, "name": "starter-suid", "nice": 0, "uids": {"real": 9182, "effetive": 9182, "saved": 0}, "cpu_affinity": [0, 1, 2, 3, 4, 5, 6, 7, 14], "status": "sleeping", "num_ctx_switches": {"voluntary": 83, "involuntary": 8}, "create_time": 1558275214.15, "SET_NPROC": "15", "ACTUAL_NPROC": "1", "HOSTNAME": "sh-07-27.int", "MAXMEMORY": "12", "SECONDS": "20"}, {"memory_percent": 0.01361330322989196, "pid": 39238, "cpu_num": 6, "ppid": 39234, "ionice": {"ioclass": "IOPRIO_CLASS_NONE", "value": 0}, "username": "vsochat", "cpu_times": {"user": 0.12, "system": 0.04, "children_user": 0.01, "children_system": 0.0}, "gids": {"real": 32264, "effetive": 32264, "saved": 32264}, "cmdline": ["Singularity runtime parent"], "num_threads": 7, "cpu_percent": 0.0, "name": "starter-suid", "nice": 0, "uids": {"real": 9182, "effetive": 9182, "saved": 0}, "cpu_affinity": [0, 1, 2, 3, 4, 5, 6, 7, 14], "status": "sleeping", "num_ctx_switches": {"voluntary": 83, "involuntary": 8}, "create_time": 1558275214.15, "SET_NPROC": "15", "ACTUAL_NPROC": "1", "HOSTNAME": "sh-07-27.int", "MAXMEMORY": "12", "SECONDS": "20"}, {"memory_percent": 0.01361330322989196, "pid": 39238, "cpu_num": 6, "ppid": 39234, "ionice": {"ioclass": "IOPRIO_CLASS_NONE", "value": 0}, "username": "vsochat", "cpu_times": {"user": 0.12, "system": 0.04, "children_user": 0.01, "children_system": 0.0}, "gids": {"real": 32264, "effetive": 32264, "saved": 32264}, "cmdline": ["Singularity runtime parent"], "num_threads": 7, "cpu_percent": 0.0, "name": "starter-suid", "nice": 0, "uids": {"real": 9182, "effetive": 9182, "saved": 0}, "cpu_affinity": [0, 1, 2, 3, 4, 5, 6, 7, 14], "status": "sleeping", "num_ctx_switches": {"voluntary": 83, "involuntary": 8}, "create_time": 1558275214.15, "SET_NPROC": "15", "ACTUAL_NPROC": "1", "HOSTNAME": "sh-07-27.int", "MAXMEMORY": "12", "SECONDS": "20"}, {"memory_percent": 0.01361330322989196, "pid": 39238, "cpu_num": 6, "ppid": 39234, "ionice": {"ioclass": "IOPRIO_CLASS_NONE", "value": 0}, "username": "vsochat", "cpu_times": {"user": 0.12, "system": 0.04, "children_user": 0.01, "children_system": 0.0}, "gids": {"real": 32264, "effetive": 32264, "saved": 32264}, "cmdline": ["Singularity runtime parent"], "num_threads": 7, "cpu_percent": 0.0, "name": "starter-suid", "nice": 0, "uids": {"real": 9182, "effetive": 9182, "saved": 0}, "cpu_affinity": [0, 1, 2, 3, 4, 5, 6, 7, 14], "status": "sleeping", "num_ctx_switches": {"voluntary": 83, "involuntary": 8}, "create_time": 1558275214.15, "SET_NPROC": "15", "ACTUAL_NPROC": "1", "HOSTNAME": "sh-07-27.int", "MAXMEMORY": "12", "SECONDS": "20"}, {"memory_percent": 0.01361330322989196, "pid": 39238, "cpu_num": 6, "ppid": 39234, "ionice": {"ioclass": "IOPRIO_CLASS_NONE", "value": 0}, "username": "vsochat", "cpu_times": {"user": 0.12, "system": 0.04, "children_user": 0.01, "children_system": 0.0}, "gids": {"real": 32264, "effetive": 32264, "saved": 32264}, "cmdline": ["Singularity runtime parent"], "num_threads": 7, "cpu_percent": 0.0, "name": "starter-suid", "nice": 0, "uids": {"real": 9182, "effetive": 9182, "saved": 0}, "cpu_affinity": [0, 1, 2, 3, 4, 5, 6, 7, 14], "status": "sleeping", "num_ctx_switches": {"voluntary": 83, "involuntary": 8}, "create_time": 1558275214.15, "SET_NPROC": "15", "ACTUAL_NPROC": "1", "HOSTNAME": "sh-07-27.int", "MAXMEMORY": "12", "SECONDS": "20"}, {"memory_percent": 0.01361330322989196, "pid": 39238, "cpu_num": 6, "ppid": 39234, "ionice": {"ioclass": "IOPRIO_CLASS_NONE", "value": 0}, "username": "vsochat", "cpu_times": {"user": 0.12, "system": 0.04, "children_user": 0.01, "children_system": 0.0}, "gids": {"real": 32264, "effetive": 32264, "saved": 32264}, "cmdline": ["Singularity runtime parent"], "num_threads": 7, "cpu_percent": 0.0, "name": "starter-suid", "nice": 0, "uids": {"real": 9182, "effetive": 9182, "saved": 0}, "cpu_affinity": [0, 1, 2, 3, 4, 5, 6, 7, 14], "status": "sleeping", "num_ctx_switches": {"voluntary": 83, "involuntary": 8}, "create_time": 1558275214.15, "SET_NPROC": "15", "ACTUAL_NPROC": "1", "HOSTNAME": "sh-07-27.int", "MAXMEMORY": "12", "SECONDS": "20"}, {"memory_percent": 0.01361330322989196, "pid": 39238, "cpu_num": 6, "ppid": 39234, "ionice": {"ioclass": "IOPRIO_CLASS_NONE", "value": 0}, "username": "vsochat", "cpu_times": {"user": 0.12, "system": 0.04, "children_user": 0.01, "children_system": 0.0}, "gids": {"real": 32264, "effetive": 32264, "saved": 32264}, "cmdline": ["Singularity runtime parent"], "num_threads": 7, "cpu_percent": 0.0, "name": "starter-suid", "nice": 0, "uids": {"real": 9182, "effetive": 9182, "saved": 0}, "cpu_affinity": [0, 1, 2, 3, 4, 5, 6, 7, 14], "status": "sleeping", "num_ctx_switches": {"voluntary": 83, "involuntary": 8}, "create_time": 1558275214.15, "SET_NPROC": "15", "ACTUAL_NPROC": "1", "HOSTNAME": "sh-07-27.int", "MAXMEMORY": "12", "SECONDS": "20"}, {"memory_percent": 0.01361330322989196, "pid": 39238, "cpu_num": 6, "ppid": 39234, "ionice": {"ioclass": "IOPRIO_CLASS_NONE", "value": 0}, "username": "vsochat", "cpu_times": {"user": 0.12, "system": 0.04, "children_user": 0.01, "children_system": 0.0}, "gids": {"real": 32264, "effetive": 32264, "saved": 32264}, "cmdline": ["Singularity runtime parent"], "num_threads": 7, "cpu_percent": 0.0, "name": "starter-suid", "nice": 0, "uids": {"real": 9182, "effetive": 9182, "saved": 0}, "cpu_affinity": [0, 1, 2, 3, 4, 5, 6, 7, 14], "status": "sleeping", "num_ctx_switches": {"voluntary": 83, "involuntary": 8}, "create_time": 1558275214.15, "SET_NPROC": "15", "ACTUAL_NPROC": "1", "HOSTNAME": "sh-07-27.int", "MAXMEMORY": "12", "SECONDS": "20"}, {"memory_percent": 0.01361330322989196, "pid": 39238, "cpu_num": 6, "ppid": 39234, "ionice": {"ioclass": "IOPRIO_CLASS_NONE", "value": 0}, "username": "vsochat", "cpu_times": {"user": 0.12, "system": 0.04, "children_user": 0.01, "children_system": 0.0}, "gids": {"real": 32264, "effetive": 32264, "saved": 32264}, "cmdline": ["Singularity runtime parent"], "num_threads": 7, "cpu_percent": 0.0, "name": "starter-suid", "nice": 0, "uids": {"real": 9182, "effetive": 9182, "saved": 0}, "cpu_affinity": [0, 1, 2, 3, 4, 5, 6, 7, 14], "status": "sleeping", "num_ctx_switches": {"voluntary": 83, "involuntary": 8}, "create_time": 1558275214.15, "SET_NPROC": "15", "ACTUAL_NPROC": "1", "HOSTNAME": "sh-07-27.int", "MAXMEMORY": "12", "SECONDS": "20"}, {"memory_percent": 0.013588895693845537, "pid": 39238, "cpu_num": 6, "ppid": 39234, "ionice": {"ioclass": "IOPRIO_CLASS_NONE", "value": 0}, "username": "vsochat", "cpu_times": {"user": 0.12, "system": 0.04, "children_user": 0.01, "children_system": 0.0}, "gids": {"real": 32264, "effetive": 32264, "saved": 32264}, "cmdline": ["Singularity runtime parent"], "num_threads": 7, "cpu_percent": 0.0, "name": "starter-suid", "nice": 0, "uids": {"real": 9182, "effetive": 9182, "saved": 0}, "cpu_affinity": [0, 1, 2, 3, 4, 5, 6, 7, 14], "status": "sleeping", "num_ctx_switches": {"voluntary": 83, "involuntary": 8}, "create_time": 1558275214.15, "SET_NPROC": "15", "ACTUAL_NPROC": "1", "HOSTNAME": "sh-07-27.int", "MAXMEMORY": "12", "SECONDS": "20"}, {"memory_percent": 0.013588895693845537, "pid": 39238, "cpu_num": 6, "ppid": 39234, "ionice": {"ioclass": "IOPRIO_CLASS_NONE", "value": 0}, "username": "vsochat", "cpu_times": {"user": 0.12, "system": 0.04, "children_user": 0.01, "children_system": 0.0}, "gids": {"real": 32264, "effetive": 32264, "saved": 32264}, "cmdline": ["Singularity runtime parent"], "num_threads": 7, "cpu_percent": 0.0, "name": "starter-suid", "nice": 0, "uids": {"real": 9182, "effetive": 9182, "saved": 0}, "cpu_affinity": [0, 1, 2, 3, 4, 5, 6, 7, 14], "status": "sleeping", "num_ctx_switches": {"voluntary": 83, "involuntary": 8}, "create_time": 1558275214.15, "SET_NPROC": "15", "ACTUAL_NPROC": "1", "HOSTNAME": "sh-07-27.int", "MAXMEMORY": "12", "SECONDS": "20"}, {"memory_percent": 0.013588895693845537, "pid": 39238, "cpu_num": 6, "ppid": 39234, "ionice": {"ioclass": "IOPRIO_CLASS_NONE", "value": 0}, "username": "vsochat", "cpu_times": {"user": 0.12, "system": 0.04, "children_user": 0.01, "children_system": 0.0}, "gids": {"real": 32264, "effetive": 32264, "saved": 32264}, "cmdline": ["Singularity runtime parent"], "num_threads": 7, "cpu_percent": 0.0, "name": "starter-suid", "nice": 0, "uids": {"real": 9182, "effetive": 9182, "saved": 0}, "cpu_affinity": [0, 1, 2, 3, 4, 5, 6, 7, 14], "status": "sleeping", "num_ctx_switches": {"voluntary": 83, "involuntary": 8}, "create_time": 1558275214.15, "SET_NPROC": "15", "ACTUAL_NPROC": "1", "HOSTNAME": "sh-07-27.int", "MAXMEMORY": "12", "SECONDS": "20"}, {"memory_percent": 0.013588895693845537, "pid": 39238, "cpu_num": 6, "ppid": 39234, "ionice": {"ioclass": "IOPRIO_CLASS_NONE", "value": 0}, "username": "vsochat", "cpu_times": {"user": 0.12, "system": 0.04, "children_user": 0.01, "children_system": 0.0}, "gids": {"real": 32264, "effetive": 32264, "saved": 32264}, "cmdline": ["Singularity runtime parent"], "num_threads": 7, "cpu_percent": 0.0, "name": "starter-suid", "nice": 0, "uids": {"real": 9182, "effetive": 9182, "saved": 0}, "cpu_affinity": [0, 1, 2, 3, 4, 5, 6, 7, 14], "status": "sleeping", "num_ctx_switches": {"voluntary": 83, "involuntary": 8}, "create_time": 1558275214.15, "SET_NPROC": "15", "ACTUAL_NPROC": "1", "HOSTNAME": "sh-07-27.int", "MAXMEMORY": "12", "SECONDS": "20"}, {"memory_percent": 0.013588895693845537, "pid": 39238, "cpu_num": 6, "ppid": 39234, "ionice": {"ioclass": "IOPRIO_CLASS_NONE", "value": 0}, "username": "vsochat", "cpu_times": {"user": 0.12, "system": 0.04, "children_user": 0.01, "children_system": 0.0}, "gids": {"real": 32264, "effetive": 32264, "saved": 32264}, "cmdline": ["Singularity runtime parent"], "num_threads": 7, "cpu_percent": 0.0, "name": "starter-suid", "nice": 0, "uids": {"real": 9182, "effetive": 9182, "saved": 0}, "cpu_affinity": [0, 1, 2, 3, 4, 5, 6, 7, 14], "status": "sleeping", "num_ctx_switches": {"voluntary": 83, "involuntary": 8}, "create_time": 1558275214.15, "SET_NPROC": "15", "ACTUAL_NPROC": "1", "HOSTNAME": "sh-07-27.int", "MAXMEMORY": "12", "SECONDS": "20"}, {"memory_percent": 0.013588895693845537, "pid": 39238, "cpu_num": 6, "ppid": 39234, "ionice": {"ioclass": "IOPRIO_CLASS_NONE", "value": 0}, "username": "vsochat", "cpu_times": {"user": 0.12, "system": 0.04, "children_user": 0.01, "children_system": 0.0}, "gids": {"real": 32264, "effetive": 32264, "saved": 32264}, "cmdline": ["Singularity runtime parent"], "num_threads": 7, "cpu_percent": 0.0, "name": "starter-suid", "nice": 0, "uids": {"real": 9182, "effetive": 9182, "saved": 0}, "cpu_affinity": [0, 1, 2, 3, 4, 5, 6, 7, 14], "status": "sleeping", "num_ctx_switches": {"voluntary": 83, "involuntary": 8}, "create_time": 1558275214.15, "SET_NPROC": "15", "ACTUAL_NPROC": "1", "HOSTNAME": "sh-07-27.int", "MAXMEMORY": "12", "SECONDS": "20"}, {"memory_percent": 0.013588895693845537, "pid": 39238, "cpu_num": 6, "ppid": 39234, "ionice": {"ioclass": "IOPRIO_CLASS_NONE", "value": 0}, "username": "vsochat", "cpu_times": {"user": 0.12, "system": 0.04, "children_user": 0.01, "children_system": 0.0}, "gids": {"real": 32264, "effetive": 32264, "saved": 32264}, "cmdline": ["Singularity runtime parent"], "num_threads": 7, "cpu_percent": 0.0, "name": "starter-suid", "nice": 0, "uids": {"real": 9182, "effetive": 9182, "saved": 0}, "cpu_affinity": [0, 1, 2, 3, 4, 5, 6, 7, 14], "status": "sleeping", "num_ctx_switches": {"voluntary": 83, "involuntary": 8}, "create_time": 1558275214.15, "SET_NPROC": "15", "ACTUAL_NPROC": "1", "HOSTNAME": "sh-07-27.int", "MAXMEMORY": "12", "SECONDS": "20"}, {"memory_percent": 0.013588895693845537, "pid": 39238, "cpu_num": 6, "ppid": 39234, "ionice": {"ioclass": "IOPRIO_CLASS_NONE", "value": 0}, "username": "vsochat", "cpu_times": {"user": 0.12, "system": 0.04, "children_user": 0.01, "children_system": 0.0}, "gids": {"real": 32264, "effetive": 32264, "saved": 32264}, "cmdline": ["Singularity runtime parent"], "num_threads": 7, "cpu_percent": 0.0, "name": "starter-suid", "nice": 0, "uids": {"real": 9182, "effetive": 9182, "saved": 0}, "cpu_affinity": [0, 1, 2, 3, 4, 5, 6, 7, 14], "status": "sleeping", "num_ctx_switches": {"voluntary": 83, "involuntary": 8}, "create_time": 1558275214.15, "SET_NPROC": "15", "ACTUAL_NPROC": "1", "HOSTNAME": "sh-07-27.int", "MAXMEMORY": "12", "SECONDS": "20"}, {"memory_percent": 0.013588895693845537, "pid": 39238, "cpu_num": 6, "ppid": 39234, "ionice": {"ioclass": "IOPRIO_CLASS_NONE", "value": 0}, "username": "vsochat", "cpu_times": {"user": 0.12, "system": 0.04, "children_user": 0.01, "children_system": 0.0}, "gids": {"real": 32264, "effetive": 32264, "saved": 32264}, "cmdline": ["Singularity runtime parent"], "num_threads": 7, "cpu_percent": 0.0, "name": "starter-suid", "nice": 0, "uids": {"real": 9182, "effetive": 9182, "saved": 0}, "cpu_affinity": [0, 1, 2, 3, 4, 5, 6, 7, 14], "status": "sleeping", "num_ctx_switches": {"voluntary": 83, "involuntary": 8}, "create_time": 1558275214.15, "SET_NPROC": "15", "ACTUAL_NPROC": "1", "HOSTNAME": "sh-07-27.int", "MAXMEMORY": "12", "SECONDS": "20"}, {"memory_percent": 0.013588895693845537, "pid": 39238, "cpu_num": 6, "ppid": 39234, "ionice": {"ioclass": "IOPRIO_CLASS_NONE", "value": 0}, "username": "vsochat", "cpu_times": {"user": 0.12, "system": 0.04, "children_user": 0.01, "children_system": 0.0}, "gids": {"real": 32264, "effetive": 32264, "saved": 32264}, "cmdline": ["Singularity runtime parent"], "num_threads": 7, "cpu_percent": 0.0, "name": "starter-suid", "nice": 0, "uids": {"real": 9182, "effetive": 9182, "saved": 0}, "cpu_affinity": [0, 1, 2, 3, 4, 5, 6, 7, 14], "status": "sleeping", "num_ctx_switches": {"voluntary": 83, "involuntary": 8}, "create_time": 1558275214.15, "SET_NPROC": "15", "ACTUAL_NPROC": "1", "HOSTNAME": "sh-07-27.int", "MAXMEMORY": "12", "SECONDS": "20"}]
